Metadata-Version: 2.1
Name: nepali-g2p
Version: 0.1.0
Summary: A simple Nepali G2P conversion library
Home-page: https://github.com/ashokgit/g2p-nepali
Author: Ashok Poudel
Author-email: ashok.poudel@gmail.com
License: UNKNOWN
Platform: UNKNOWN
Classifier: Development Status :: 3 - Alpha
Classifier: License :: OSI Approved :: MIT License
Classifier: Programming Language :: Python :: 3
Classifier: Programming Language :: Python :: 3.6
Classifier: Programming Language :: Python :: 3.7
Classifier: Programming Language :: Python :: 3.8
Classifier: Programming Language :: Python :: 3.9
